{
  "StoreName": "Burger Palace",
  "Latitude": 55.64501,
  "Longitude": 96.132548,
  "FoodCategory": "bbq",
  "Stars": 3.9,
  "NoOfVotes": 337,
  "StoreLogo": "/images/burger_palace_logo.png",
  "Products": [
    {
      "ProductName": "Brisket Plate",
      "ProductType": "bbq",
      "Available Amount": 654,
      "Price": 5.64
    },
    {
      "ProductName": "BBQ Ribs",
      "ProductType": "bbq",
      "Available Amount": 849,
      "Price": 3.34
    },
    {
      "ProductName": "Pulled Pork Sandwich",
      "ProductType": "bbq",
      "Available Amount": 101,
      "Price": 7.28
    }
  ]
}