{
  "StoreName": "Fresh Bite",
  "Latitude": -24.484712,
  "Longitude": 93.331674,
  "FoodCategory": "sushi",
  "Stars": 2.7,
  "NoOfVotes": 387,
  "StoreLogo": "/images/fresh_bite_logo.png",
  "Products": [
    {
      "ProductName": "Salmon Nigiri",
      "ProductType": "sushi",
      "Available Amount": 729,
      "Price": 6.77
    },
    {
      "ProductName": "Spicy Tuna Roll",
      "ProductType": "sushi",
      "Available Amount": 549,
      "Price": 5.46
    },
    {
      "ProductName": "California Roll",
      "ProductType": "sushi",
      "Available Amount": 850,
      "Price": 4.05
    }
  ]
}